bo_guan_yue_qu/__init__.py
bo_guan_yue_qu/prefix_tuning.py
bo_guan_yue_qu-0.1.0.dist-info/LICENSE
bo_guan_yue_qu-0.1.0.dist-info/WHEEL
bo_guan_yue_qu-0.1.0.dist-info/METADATA
bo_guan_yue_qu-0.1.0.dist-info/RECORD
